vending_machine.v

module vending_machine(
    input clk,
    input reset,
    input [1:0] coin,   // 00=none, 01=5Rs, 10=10Rs, 11=invalid
    output reg dispense,
    output reg return5,
    output reg [2:0] current_state
);

    // State encoding
    localparam S0   = 3'b000;
    localparam S5   = 3'b001;
    localparam S10  = 3'b010;
    localparam S15  = 3'b011;
    localparam DISP = 3'b100;
    localparam CHG  = 3'b101;

    reg [2:0] next_state;

    // Sequential logic
    always @(posedge clk or posedge reset) begin
        if (reset)
            current_state <= S0;
        else
            current_state <= next_state;
    end

    // Output logic
    always @(*) begin
        dispense = 0;
        return5 = 0;

        case (current_state)
            DISP: dispense = 1;
            CHG : return5 = 1;
        endcase
    end

    // Next state logic
    always @(*) begin
        next_state = current_state;

        case (current_state)

            S0 : begin
                case (coin)
                    2'b01: next_state = S5;          // +5
                    2'b10: next_state = S10;         // +10
                    default: next_state = S0;        // invalid/no coin
                endcase
            end

            S5 : begin
                case (coin)
                    2'b01: next_state = S10;         // +5 ? 10
                    2'b10: next_state = S15;         // +10 ? 15
                    default: next_state = S5;
                endcase
            end

            S10 : begin
                case (coin)
                    2'b01: next_state = S15;         // +5 ? 15
                    2'b10: next_state = CHG;         // +10 ? 20 ? return 5
                    default: next_state = S10;
                endcase
            end

            S15 : next_state = DISP;                 // automatic

            DISP: next_state = S0;                   // auto-reset

            CHG : next_state = S0;                   // auto-reset

        endcase
    end

endmodule

vending_machine_tb.v
`timescale 1ns/1ps

module vending_machine_tb;

    reg clk;
    reg reset;
    reg [1:0] coin;       // 00=no coin, 01=5Rs, 10=10Rs, 11=invalid
    wire dispense;
    wire return5;
    wire [2:0] state;

    // DUT instantiation
    vending_machine dut (
        .clk(clk),
        .reset(reset),
        .coin(coin),
        .dispense(dispense),
        .return5(return5),
        .current_state(state)
    );

    // Clock generator
    always #5 clk = ~clk;   // 10ns clock period

    // Task to insert coin
    task insert_coin(input [1:0] c);
    begin
        coin = c;
        #10;
        coin = 2'b00;  // remove coin signal after 1 cycle
        #10;
    end
    endtask

    // Display state names (for readability)
    task print_state;
    begin
        case (state)
            3'b000: $display("Time=%0t : State = S0 (Rs 0)", $time);
            3'b001: $display("Time=%0t : State = S5 (Rs 5)", $time);
            3'b010: $display("Time=%0t : State = S10 (Rs 10)", $time);
            3'b011: $display("Time=%0t : State = S15 (Rs 15)", $time);
            3'b100: $display("Time=%0t : State = DISPENSE", $time);
            3'b101: $display("Time=%0t : State = RETURN 5Rs", $time);
            default: $display("Time=%0t : State = UNKNOWN", $time);
        endcase
    end
    endtask

    // Main Test Sequence
    initial begin
        $dumpfile("vending_machine_tb.vcd");
        $dumpvars(0, vending_machine_tb);

        clk = 0;
        coin = 0;

        // 1. Apply reset
        reset = 1;
        #20;
        reset = 0;
        print_state();

        // 2. Scenario 1: 5 + 5 + 5 => DISPENSE
        $display("\n=== TEST 1: 5 + 5 + 5 ===");
        insert_coin(2'b01); print_state();
        insert_coin(2'b01); print_state();
        insert_coin(2'b01); print_state();
        #20; print_state();

        // 3. Scenario 2: 10 + 5 => DISPENSE
        $display("\n=== TEST 2: 10 + 5 ===");
        insert_coin(2'b10); print_state();
        insert_coin(2'b01); print_state();
        #20; print_state();

        // 4. Scenario 3: 5 + 10 => DISPENSE
        $display("\n=== TEST 3: 5 + 10 ===");
        insert_coin(2'b01); print_state();
        insert_coin(2'b10); print_state();
        #20; print_state();

        // 5. Scenario 4: 10 + 10 => RETURN ?5
        $display("\n=== TEST 4: 10 + 10 => RETURN 5 ===");
        insert_coin(2'b10); print_state();
        insert_coin(2'b10); print_state();
        #20; print_state();

        // 6. Scenario 5: Invalid coin
        $display("\n=== TEST 5: INVALID COIN ===");
        insert_coin(2'b11); print_state();
        #20; print_state();

        // 7. Scenario 6: Reset in middle of operation
        $display("\n=== TEST 6: Reset test ===");
        insert_coin(2'b01); print_state();   // Go to 5
        reset = 1; #10; reset = 0;
        print_state();

        $display("\n=== TEST COMPLETED ===");
        #100;
        $finish;
    end

endmodule

vending_machine_tb.vcd
$date
	Sun Nov 23 03:41:21 2025
$end
$version
	QuestaSim Version 10.7c
$end
$timescale
	1ps
$end

$scope module vending_machine_tb $end
$var reg 1 ! clk $end
$var reg 1 " reset $end
$var reg 2 # coin [1:0] $end
$var wire 1 $ dispense $end
$var wire 1 % return5 $end
$var wire 1 & state [2] $end
$var wire 1 ' state [1] $end
$var wire 1 ( state [0] $end

$scope task insert_coin $end
$var reg 2 ) c [1:0] $end
$upscope $end

$scope task print_state $end
$upscope $end

$scope module dut $end
$var parameter 3 * S0 $end
$var parameter 3 + S5 $end
$var parameter 3 , S10 $end
$var parameter 3 - S15 $end
$var parameter 3 . DISP $end
$var parameter 3 / CHG $end
$var wire 1 0 clk $end
$var wire 1 1 reset $end
$var wire 1 2 coin [1] $end
$var wire 1 3 coin [0] $end
$var reg 1 4 dispense $end
$var reg 1 5 return5 $end
$var reg 3 6 current_state [2:0] $end
$var reg 3 7 next_state [2:0] $end
$upscope $end
$upscope $end
$enddefinitions $end
#0
$dumpvars
0!
1"
b0 #
04
05
b0 6
b0 7
bx )
b0 *
b1 +
b10 ,
b11 -
b100 .
b101 /
0$
0%
0(
0'
0&
03
02
11
00
$end
#5000
1!
10
#10000
0!
00
#15000
1!
10
#20000
0"
b1 )
b1 #
0!
01
13
00
b1 7
#25000
1!
10
b1 6
1(
b10 7
#30000
b0 #
0!
03
00
b1 7
#35000
1!
10
#40000
b1 #
0!
13
00
b10 7
#45000
1!
10
b10 6
0(
1'
b11 7
#50000
b0 #
0!
03
00
b10 7
#55000
1!
10
#60000
b1 #
0!
13
00
b11 7
#65000
1!
10
b11 6
1(
b100 7
#70000
b0 #
0!
03
00
b11 7
b100 7
#75000
1!
10
b100 6
0(
0'
1&
14
b0 7
1$
#80000
0!
00
#85000
1!
10
b0 6
0&
04
0$
#90000
0!
00
#95000
1!
10
#100000
b10 )
b10 #
0!
12
00
b10 7
#105000
1!
10
b10 6
1'
b101 7
#110000
b0 #
0!
02
00
b10 7
#115000
1!
10
#120000
b1 )
b1 #
0!
13
00
b11 7
#125000
1!
10
b11 6
1(
b100 7
#130000
b0 #
0!
03
00
b11 7
b100 7
#135000
1!
10
b100 6
0(
0'
1&
14
b0 7
1$
#140000
0!
00
#145000
1!
10
b0 6
0&
04
0$
#150000
0!
00
#155000
1!
10
#160000
b1 #
0!
13
00
b1 7
#165000
1!
10
b1 6
1(
b10 7
#170000
b0 #
0!
03
00
b1 7
#175000
1!
10
#180000
b10 )
b10 #
0!
12
00
b11 7
#185000
1!
10
b11 6
1'
b100 7
#190000
b0 #
0!
02
00
b11 7
b100 7
#195000
1!
10
b100 6
0(
0'
1&
14
b0 7
1$
#200000
0!
00
#205000
1!
10
b0 6
0&
04
0$
#210000
0!
00
#215000
1!
10
#220000
b10 #
0!
12
00
b10 7
#225000
1!
10
b10 6
1'
b101 7
#230000
b0 #
0!
02
00
b10 7
#235000
1!
10
#240000
b10 #
0!
12
00
b101 7
#245000
1!
10
b101 6
1(
0'
1&
15
b0 7
1%
#250000
b0 #
0!
02
00
b101 7
b0 7
#255000
1!
10
b0 6
0(
0&
05
0%
#260000
0!
00
#265000
1!
10
#270000
0!
00
#275000
1!
10
#280000
b11 )
b11 #
0!
13
12
00
#285000
1!
10
#290000
b0 #
0!
03
02
00
#295000
1!
10
#300000
0!
00
#305000
1!
10
#310000
0!
00
#315000
1!
10
#320000
b1 )
b1 #
0!
13
00
b1 7
#325000
1!
10
b1 6
1(
b10 7
#330000
b0 #
0!
03
00
b1 7
#335000
1!
10
#340000
1"
0!
11
00
b0 6
0(
b0 7
#345000
1!
10
#350000
0"
0!
01
00
